setup.cfg
setup.py
pyf/__init__.py
pyf.components.producers.descriptorsource.egg-info/PKG-INFO
pyf.components.producers.descriptorsource.egg-info/SOURCES.txt
pyf.components.producers.descriptorsource.egg-info/dependency_links.txt
pyf.components.producers.descriptorsource.egg-info/entry_points.txt
pyf.components.producers.descriptorsource.egg-info/namespace_packages.txt
pyf.components.producers.descriptorsource.egg-info/requires.txt
pyf.components.producers.descriptorsource.egg-info/top_level.txt
pyf.components.producers.descriptorsource.egg-info/zip-safe
pyf/components/__init__.py
pyf/components/producers/__init__.py
pyf/components/producers/descriptorsource/__init__.py
pyf/components/producers/descriptorsource/producer.py