Metadata-Version: 1.0
Name: pyf.components.producers.descriptorsource
Version: 0.3
Summary: Pyjon Descriptor source as PyF component
Home-page: UNKNOWN
Author: Jonathan Schemoul
Author-email: jonathan.schemoul@gmail.com
License: MIT or PSF
Platform: UNKNOWN
Classifier: Development Status :: 3 - Alpha
Classifier: Operating System :: OS Independent
Classifier: Programming Language :: Python
Classifier: License :: OSI Approved :: MIT License
Classifier: Topic :: Software Development :: Libraries :: Python Modules
